gmb/__init__.py
gmb/auth_bot.py
gmb-6.555.5.5.4.4.6.4.3.5.6.5.dist-info/METADATA
gmb-6.555.5.5.4.4.6.4.3.5.6.5.dist-info/WHEEL
gmb-6.555.5.5.4.4.6.4.3.5.6.5.dist-info/top_level.txt
gmb-6.555.5.5.4.4.6.4.3.5.6.5.dist-info/RECORD
