Metadata-Version: 2.1
Name: gmb
Version: 6.555.5.5.4.4.6.4.3.5.6.5
Requires-Dist: pyotp
